top_names/__init__.py
top_names/__main__.py
top_names/name_list.py
top_names/name_scraper.py
top_names-1.2.0.dist-info/LICENSE
top_names-1.2.0.dist-info/METADATA
top_names-1.2.0.dist-info/WHEEL
top_names-1.2.0.dist-info/top_level.txt
top_names-1.2.0.dist-info/RECORD
