Metadata-Version: 2.1
Name: top-names
Version: 1.2.0
Summary: Library for scraping the top names in the United States.
Home-page: https://github.com/wciesialka/top-names
Author: Willow Ciesialka
Author-email: wciesialka@gmail.com
License: MIT
Keywords: python data list names usa
Platform: UNKNOWN
Classifier: License :: OSI Approved :: MIT License
Classifier: Programming Language :: Python :: 3
Classifier: Topic :: Internet :: WWW/HTTP :: Indexing/Search
Classifier: Operating System :: OS Independent
Requires-Python: >=3.8.10
Requires-Dist: beautifulsoup4 (==4.10.0)
Requires-Dist: bs4 (==0.0.1)
Requires-Dist: certifi (==2021.5.30)
Requires-Dist: charset-normalizer (==2.0.6)
Requires-Dist: idna (==3.2)
Requires-Dist: requests (==2.26.0)
Requires-Dist: soupsieve (==2.2.1)
Requires-Dist: urllib3 (==1.26.7)
